apiscrub/__init__.py
apiscrub/main.py
apiscrub-1.1.0.dist-info/METADATA
apiscrub-1.1.0.dist-info/RECORD
apiscrub-1.1.0.dist-info/WHEEL
apiscrub-1.1.0.dist-info/entry_points.txt
apiscrub-1.1.0.dist-info/top_level.txt
