Metadata-Version: 2.1
Name: apiscrub
Version: 1.1.0
Summary: OpenAPI Scrubber
Home-page: https://github.com/danielgtaylor/apiscrub
Author: Daniel G. Taylor
Author-email: danielgtaylor@gmail.com
License: UNKNOWN
Platform: UNKNOWN
Classifier: Programming Language :: Python :: 3
Classifier: License :: OSI Approved :: MIT License
Classifier: Operating System :: OS Independent
Requires-Dist: ruamel.yaml (>=0.15)
